veloxloop/__init__.py
veloxloop/_veloxloop.cpython-313-powerpc64le-linux-gnu.so
veloxloop/_veloxloop.pyi
veloxloop-0.2.0.dist-info/METADATA
veloxloop-0.2.0.dist-info/WHEEL
veloxloop-0.2.0.dist-info/licenses/LICENSE
veloxloop-0.2.0.dist-info/RECORD
